tornado_obj/__init__.py
tornado_obj/tornado_obj.py
tornadoobj-0.0.13.dist-info/LICENSE.txt
tornadoobj-0.0.13.dist-info/METADATA
tornadoobj-0.0.13.dist-info/WHEEL
tornadoobj-0.0.13.dist-info/top_level.txt
tornadoobj-0.0.13.dist-info/RECORD
