Metadata-Version: 2.2
Name: TornadoObj
Version: 0.0.13
Summary: Tornado
Author-email: Denis Minka <minka.denis@gmail.com>
License-File: LICENSE.txt
Requires-Dist: speeedy
Requires-Dist: loguru
